fastq_filter/_filters.cpython-310-x86_64-linux-gnu.so
fastq_filter/__main__.py
fastq_filter/_filtersmodule.c
fastq_filter/score_to_error_rate.h
fastq_filter/py.typed
fastq_filter/_filters.pyi
fastq_filter/__init__.py
fastq_filter-0.3.0.dist-info/entry_points.txt
fastq_filter-0.3.0.dist-info/LICENSE
fastq_filter-0.3.0.dist-info/top_level.txt
fastq_filter-0.3.0.dist-info/RECORD
fastq_filter-0.3.0.dist-info/METADATA
fastq_filter-0.3.0.dist-info/WHEEL
