Metadata-Version: 2.1
Name: fastq-filter
Version: 0.3.0
Summary: A fast FASTQ filter progam.
Home-page: https://github.com/lumc/fastq-filter
Author: Leiden University Medical Center
Author-email: r.h.p.vorderman@lumc.nl
License: MIT
Keywords: FASTQ filter
Classifier: Programming Language :: Python :: 3 :: Only
Classifier: Programming Language :: Python :: 3
Classifier: Programming Language :: Python :: 3.7
Classifier: Programming Language :: Python :: 3.8
Classifier: Programming Language :: Python :: 3.9
Classifier: Programming Language :: Python :: 3.10
Classifier: License :: OSI Approved :: MIT License
Requires-Python: >=3.7
License-File: LICENSE
